wxltz/__init__.py
wxltz/__main__.py
wxltz/main.py
wxltz/models.py
wxltz/utils.py
wxltz-0.1.1.dist-info/entry_points.txt
wxltz-0.1.1.dist-info/WHEEL
wxltz-0.1.1.dist-info/METADATA
wxltz-0.1.1.dist-info/RECORD
